tktabl/__init__.py
tktabl/__main__.py
tktabl-0.2.0.dist-info/LICENSE.txt
tktabl-0.2.0.dist-info/WHEEL
tktabl-0.2.0.dist-info/METADATA
tktabl-0.2.0.dist-info/RECORD
