Metadata-Version: 2.1
Name: tktabl
Version: 0.2.0
Summary: Python Tkinter Table complement
Home-page: https://github.com/DaShagy/python-tktable
License: MIT
Keywords: tkinter,complement,gui
Author: Juan José Abuin
Author-email: juanj.abuin@gmail.com
Requires-Python: >=3.9,<4.0
Classifier: License :: OSI Approved :: MIT License
Classifier: Programming Language :: Python :: 3
Classifier: Programming Language :: Python :: 3.9
Project-URL: Repository, https://github.com/DaShagy/python-tktable
